.gitignore
LICENSE
MANIFEST.in
README.md
setup.py
.github/workflows/unit_tests.yml
coffeine/__init__.py
coffeine/covariance_transformers.py
coffeine/pipelines.py
coffeine/power_features.py
coffeine/spatial_filters.py
coffeine.egg-info/PKG-INFO
coffeine.egg-info/SOURCES.txt
coffeine.egg-info/dependency_links.txt
coffeine.egg-info/requires.txt
coffeine.egg-info/top_level.txt
coffeine/tests/test_pipelines.py
coffeine/tests/test_power_features.py
coffeine/tests/test_spatial_filters.py