Metadata-Version: 2.1
Name: coffeine
Version: 0.1
Summary: M/EEG power regression pipelines in Python
Home-page: https://github.com/coffeine-labs/coffeine
Maintainer: Denis Engemann
Maintainer-email: denis.engemann@gmail.com
License: MIT
Download-URL: https://github.com/coffeine-labs/coffeine.git
Platform: any
Classifier: Intended Audience :: Science/Research
Classifier: Intended Audience :: Developers
Classifier: License :: OSI Approved
Classifier: Programming Language :: Python
Classifier: Topic :: Software Development
Classifier: Topic :: Scientific/Engineering
Classifier: Operating System :: Microsoft :: Windows
Classifier: Operating System :: POSIX
Classifier: Operating System :: Unix
Classifier: Operating System :: MacOS
Requires-Python: >=3
